edugine/__init__.py
edugine/widget.py
edugine/core/__init__.py
edugine/core/gui.py
edugine/gridgame/__init__.py
edugine/gridgame/core/__init__.py
edugine/gridgame/core/controllers.py
edugine/gridgame/core/models.py
edugine/gridgame/pyglet/__init__.py
edugine/pyglet/__init__.py
edugine/pyglet/gui.py
edugine-0.1.dev4.dist-info/LICENSE
edugine-0.1.dev4.dist-info/METADATA
edugine-0.1.dev4.dist-info/WHEEL
edugine-0.1.dev4.dist-info/top_level.txt
edugine-0.1.dev4.dist-info/RECORD
