Metadata-Version: 2.1
Name: edugine
Version: 0.1.dev4
Summary: UNKNOWN
Home-page: https://github.com/hl037/edugine
Author: Léo Flaventin Hauchecorne
Author-email: hl037.prog@gmail.com
License: GPLv3
Platform: UNKNOWN
Classifier: Development Status :: 3 - Alpha
Classifier: Intended Audience :: Education
Classifier: License :: OSI Approved :: GNU General Public License v3 (GPLv3)
Classifier: Operating System :: OS Independent
Classifier: Programming Language :: Python
Classifier: Topic :: Games/Entertainment
Classifier: Topic :: Games/Entertainment :: Arcade
Classifier: Topic :: Software Development :: Libraries :: Application Frameworks
License-File: LICENSE
Requires-Dist: numpy
Requires-Dist: pyglet
Requires-Dist: icecream
Requires-Dist: scipy
